fix_plugin_vsphere/__init__.py
fix_plugin_vsphere/config.py
fix_plugin_vsphere/resources.py
fix_plugin_vsphere/vsphere_client.py
fixinventory_plugin_vsphere-4.1.2.dist-info/LICENSE
fixinventory_plugin_vsphere-4.1.2.dist-info/METADATA
fixinventory_plugin_vsphere-4.1.2.dist-info/WHEEL
fixinventory_plugin_vsphere-4.1.2.dist-info/entry_points.txt
fixinventory_plugin_vsphere-4.1.2.dist-info/top_level.txt
fixinventory_plugin_vsphere-4.1.2.dist-info/RECORD
