Metadata-Version: 2.1
Name: fixinventory-plugin-vsphere
Version: 4.1.2
Summary: Fix vSphere Collector Plugin
Author: Some Engineering Inc.
License: 
Project-URL: Documentation, https://inventory.fix.security
Project-URL: Source, https://github.com/someengineering/fixinventory-plugin-vsphere
Classifier: Development Status :: 4 - Beta
Classifier: Intended Audience :: System Administrators
Classifier: Intended Audience :: Information Technology
Classifier: License :: OSI Approved :: Apache Software License
Classifier: Programming Language :: Python :: 3.12
Classifier: Operating System :: POSIX :: Linux
Classifier: Operating System :: Unix
Classifier: Environment :: Console
Classifier: Natural Language :: English
Classifier: Topic :: Security
Classifier: Topic :: Utilities
Requires-Python: >=3.12
License-File: LICENSE
Requires-Dist: fixinventorylib>=4.1.0
Requires-Dist: pyvmomi
Provides-Extra: test
Requires-Dist: black; extra == "test"
Requires-Dist: coverage; extra == "test"
Requires-Dist: flake8; extra == "test"
Requires-Dist: hypothesis; extra == "test"
Requires-Dist: mypy; extra == "test"
Requires-Dist: pep8-naming; extra == "test"
Requires-Dist: pylint; extra == "test"
Requires-Dist: pytest; extra == "test"
Requires-Dist: pytest-asyncio; extra == "test"
Requires-Dist: pytest-cov; extra == "test"
Requires-Dist: pytest-runner; extra == "test"
Requires-Dist: pytest-mock; extra == "test"
Requires-Dist: tox; extra == "test"
Requires-Dist: wheel; extra == "test"
